pylipsum/__init__.py
pylipsum/main.py
pylipsum-11.post20240612.dist-info/METADATA
pylipsum-11.post20240612.dist-info/WHEEL
pylipsum-11.post20240612.dist-info/top_level.txt
pylipsum-11.post20240612.dist-info/RECORD
