Metadata-Version: 2.1
Name: pylipsum
Version: 11.post20240612
Summary: Lorem lipsum as py library
Home-page: UNKNOWN
Author-email: diassuikimbek@aol.com
License: UNKNOWN
Platform: UNKNOWN
